setup.py
m_minepy.egg-info/PKG-INFO
m_minepy.egg-info/SOURCES.txt
m_minepy.egg-info/dependency_links.txt
m_minepy.egg-info/top_level.txt
minepy/__init__.py
minepy/minepy.py