Metadata-Version: 1.0
Name: m-minepy
Version: 1.0.0
Summary: A useful module
Home-page: UNKNOWN
Author: Man minepy
Author-email: minepymail@minepy.com
License: UNKNOWN
Platform: UNKNOWN
